pykef/__init__.py
pykef-1.3.0.dist-info/LICENSE
pykef-1.3.0.dist-info/METADATA
pykef-1.3.0.dist-info/WHEEL
pykef-1.3.0.dist-info/top_level.txt
pykef-1.3.0.dist-info/RECORD
