Metadata-Version: 2.1
Name: pykef
Version: 1.3.0
Summary: A python implementation to interface Kef speakers over tcp/ip
Home-page: https://github.com/Gronis/pykef/
Author: Robin Grönberg
Author-email: robingronberg@gmail.com
License: UNKNOWN
Platform: UNKNOWN
Classifier: Programming Language :: Python :: 3
Classifier: License :: OSI Approved :: MIT License
Classifier: Operating System :: OS Independent
